<?xml version="1.0" encoding="UTF-8"?>
<Track name="RandomZigZag-4" type="Sprint"><OuterBoundaries><Point id="0" x="3" y="22" /><Point id="1" x="2" y="22" /><Point id="2" x="2" y="28" /><Point id="3" x="8" y="28" /><Point id="4" x="29" y="28" /><Point id="5" x="35" y="28" /><Point id="6" x="35" y="22" /><Point id="7" x="35" y="8" /><Point id="8" x="50" y="8" /><Point id="9" x="50" y="23" /><Point id="10" x="50" y="29" /><Point id="11" x="56" y="29" /><Point id="12" x="74" y="29" /><Point id="13" x="74" y="41" /><Point id="14" x="57" y="41" /></OuterBoundaries><InnerBoundaries><Point id="0" x="3" y="22" /><Point id="1" x="8" y="22" /><Point id="2" x="29" y="22" /><Point id="3" x="29" y="8" /><Point id="4" x="29" y="2" /><Point id="5" x="35" y="2" /><Point id="6" x="50" y="2" /><Point id="7" x="56" y="2" /><Point id="8" x="56" y="8" /><Point id="9" x="56" y="23" /><Point id="10" x="74" y="23" /><Point id="11" x="80" y="23" /><Point id="12" x="80" y="29" /><Point id="13" x="80" y="41" /><Point id="14" x="80" y="47" /><Point id="15" x="74" y="47" /><Point id="16" x="57" y="47" /><Point id="17" x="51" y="47" /><Point id="18" x="51" y="41" /></InnerBoundaries><Dimension width="82" height="49" /><StartingPositions><Point x="3" y="23" /><Point x="3" y="24" /><Point x="3" y="25" /><Point x="3" y="26" /><Point x="3" y="27" /></StartingPositions></Track>
